epsilon/__init__.py
epsilon/_version.py
epsilon/ampauth.py
epsilon/amprouter.py
epsilon/asplode.py
epsilon/caseless.py
epsilon/compat.py
epsilon/cooperator.py
epsilon/descriptor.py
epsilon/expose.py
epsilon/extime.py
epsilon/hotfix.py
epsilon/iepsilon.py
epsilon/juice.py
epsilon/liner.py
epsilon/modal.py
epsilon/pending.py
epsilon/process.py
epsilon/react.py
epsilon/remember.py
epsilon/setuphelper.py
epsilon/spewer.py
epsilon/structlike.py
epsilon/unrepr.py
epsilon/view.py
epsilon/hotfixes/__init__.py
epsilon/hotfixes/deferredgenerator_tfailure.py
epsilon/hotfixes/delayedcall_seconds.py
epsilon/hotfixes/filepath_copyTo.py
epsilon/hotfixes/internet_task_clock.py
epsilon/hotfixes/loopbackasync_reentrancy.py
epsilon/hotfixes/plugin_package_paths.py
epsilon/hotfixes/proto_helpers_stringtransport.py
epsilon/hotfixes/timeoutmixin_calllater.py
epsilon/hotfixes/trial_assertwarns.py
epsilon/scripts/__init__.py
epsilon/scripts/benchmark.py
epsilon/scripts/certcreate.py
epsilon/test/__init__.py
epsilon/test/iosim.py
epsilon/test/mantissa-structure.py
epsilon/test/test_ampauth.py
epsilon/test/test_amprouter.py
epsilon/test/test_benchmark.py
epsilon/test/test_caseless.py
epsilon/test/test_descriptor.py
epsilon/test/test_expose.py
epsilon/test/test_extime.py
epsilon/test/test_juice.py
epsilon/test/test_modes.py
epsilon/test/test_process.py
epsilon/test/test_react.py
epsilon/test/test_remember.py
epsilon/test/test_setuphelper.py
epsilon/test/test_structlike.py
epsilon/test/test_unrepr.py
epsilon/test/test_version.py
epsilon/test/test_view.py
epsilon/test/utils.py
epsilon-0.8.0.data/scripts/benchmark
epsilon-0.8.0.data/scripts/certcreate
epsilon-0.8.0.dist-info/LICENSE
epsilon-0.8.0.dist-info/METADATA
epsilon-0.8.0.dist-info/WHEEL
epsilon-0.8.0.dist-info/top_level.txt
epsilon-0.8.0.dist-info/RECORD
