Metadata-Version: 2.1
Name: epsilon
Version: 0.8.0
Summary: A set of utility modules used by Divmod projects
Home-page: https://github.com/twisted/epsilon
Author: UNKNOWN
Author-email: UNKNOWN
License: UNKNOWN
Platform: UNKNOWN
Classifier: Development Status :: 5 - Production/Stable
Classifier: Framework :: Twisted
Classifier: Intended Audience :: Developers
Classifier: License :: OSI Approved :: MIT License
Classifier: Programming Language :: Python
Classifier: Programming Language :: Python :: 2
Classifier: Programming Language :: Python :: 2.7
Classifier: Programming Language :: Python :: 3
Classifier: Programming Language :: Python :: 3.7
Classifier: Topic :: Internet
Classifier: Topic :: Security
Classifier: Topic :: Utilities
Requires-Dist: six (>=1.12.0)
Requires-Dist: zope.interface
Requires-Dist: twisted[tls] (>=13.2.0)
